{"sections":{"divider_8BUdXc":{"type":"divider","disabled":true,"settings":{"container":"container","border_height":1,"border_color":"#111111","padding_top":4,"padding_bottom":0,"reset_spacing":false}},"main-collection-heading":{"type":"main-collection-heading","blocks":{"f06a38ad-a426-42c0-a5ff-48ae0218618e":{"type":"1","settings":{"text_cl":"#111111","text_fs":30}}},"block_order":["f06a38ad-a426-42c0-a5ff-48ae0218618e"],"settings":{"layout":"container-fluid","background_heading_color":"#ffffff","breadcrumb_color":"#111111","show_banner":false,"use_collection_image":false,"min_height":0,"parallax":false,"show_overlay":false,"overlay":0,"design":"text-bellow-image","text_postion":"text-center"}},"8498460c-0376-40d1-bafc-199edbe0edfc":{"type":"collection-list","blocks":{"981b08cc-5195-40cd-b5f4-79c51acd6dbb":{"type":"collection_item","settings":{"title_collection":"Outdoor Lights","collection":"outdoor-wall-lights"}},"template--16567751475447__8498460c-0376-40d1-bafc-199edbe0edfc-16665857567f9937b1-0":{"type":"collection_item","settings":{"title_collection":"Hall way Lights","collection":"ceiling-light-living-room"}},"template--16567751475447__8498460c-0376-40d1-bafc-199edbe0edfc-16665857567f9937b1-1":{"type":"collection_item","settings":{"title_collection":"Bed room","collection":"ceiling-lights-for-bedroom-lights"}},"template--16567751475447__8498460c-0376-40d1-bafc-199edbe0edfc-16665857567f9937b1-3":{"type":"collection_item","settings":{"title_collection":"","collection":"kitchen-lighting","image":"shopify:\/\/shop_images\/2_2_11zon_b36d83fb-d99c-4290-b390-95ca912046b0.jpg"}},"616f3472-abe6-41ef-8d49-4e190d1fc5cc":{"type":"collection_item","settings":{"title_collection":"","collection":"plugin-lighting","image":"shopify:\/\/shop_images\/s-l1600_51_e97a2e96-5710-4c93-843c-f34960dc3946.jpg"}},"36a53b4a-830c-4660-a410-d73343bf9d7d":{"type":"collection_item","settings":{"title_collection":"vintage lights","collection":"pipe-lighting","image":"shopify:\/\/shop_images\/pipe-lights.jpg"}},"f2fc114d-493a-4996-a5d3-680228e6a3f0":{"type":"collection_item","settings":{"title_collection":"Cristal Lamps","collection":"glass-lights-for-cafe-restaurant","image":"shopify:\/\/shop_images\/A2_4_11zon_fe1d1f20-b87b-48ba-ba12-da2eab798e8e.jpg"}},"template--16567751475447__8498460c-0376-40d1-bafc-199edbe0edfc-16665857567f9937b1-2":{"type":"collection_item","settings":{"title_collection":"Panel lights","collection":"ceiling-lights-for-panel-lights"}}},"block_order":["981b08cc-5195-40cd-b5f4-79c51acd6dbb","template--16567751475447__8498460c-0376-40d1-bafc-199edbe0edfc-16665857567f9937b1-0","template--16567751475447__8498460c-0376-40d1-bafc-199edbe0edfc-16665857567f9937b1-1","template--16567751475447__8498460c-0376-40d1-bafc-199edbe0edfc-16665857567f9937b1-3","616f3472-abe6-41ef-8d49-4e190d1fc5cc","36a53b4a-830c-4660-a410-d73343bf9d7d","f2fc114d-493a-4996-a5d3-680228e6a3f0","template--16567751475447__8498460c-0376-40d1-bafc-199edbe0edfc-16665857567f9937b1-2"],"settings":{"heading":"","description":"","text_alignment":"text-center","container":"container-fluid","background_color":"","design_layout":"carousel","design_collection":"design-1","hover_effect":"zoom","show_count_product":false,"custom_width_images":false,"width_image":200,"images_style":"radius","image_ratio":"1\/1","custom_ratio":"21:9","custom_column":6,"column_gap":30,"autoplay":true,"loop":true,"show_arrow":true,"show_bullet":false,"show_bullet_mobile":false,"reveal_on_scroll":true,"padding_top":0,"padding_bottom":0,"reset_spacing":true}},"439e38df-206c-40a8-9cd5-fc0e5f00f9d3":{"type":"spacing","disabled":true,"settings":{"spacing_desktop":30,"spacing_moible":10}},"product-grid":{"type":"main-collection-product","blocks":{"35c81196-1f20-4b1d-98e4-1bea284fe6d7":{"type":"categories","disabled":true,"settings":{"title":"Category","menu":""}},"3b46edaf-55ef-46a8-b8fe-a6eb39ade3a8":{"type":"filter_by_dynamic","settings":{}},"2039056a-3cc3-4534-a522-d35bdfbaef6c":{"type":"popular_product","disabled":true,"settings":{"title":"Featured Product","collection":"best-offer","type_product":"list","maximum":3}},"8fe431f8-91f7-4b21-a605-4b55df7293e1":{"type":"image_banner","disabled":true,"settings":{"url":"","open_link":false}}},"block_order":["35c81196-1f20-4b1d-98e4-1bea284fe6d7","3b46edaf-55ef-46a8-b8fe-a6eb39ade3a8","2039056a-3cc3-4534-a522-d35bdfbaef6c","8fe431f8-91f7-4b21-a605-4b55df7293e1"],"custom_css":[".bls__product-option {display: none !important;}"],"settings":{"layout":"container-fluid","enable_list_view":false,"products_column":6,"number_products_grid":18,"number_products_list":6,"pagination":"default","product_page_count":true,"product_sort_options":true,"progress_bar":true,"enable_sidebar":true,"sidebar_position":"dropdonw_sidebar","variant_color":"Colour, couleur, Farbe, Kleur, Farge","variant_size":"Size, Dimensione, Taille","show_count":true}},"b1a1633c-9de0-43c8-8a60-a0eddc69dfb1":{"type":"custom-liquid","settings":{"heading":"","description":"","text_alignment":"text-center","container":"container-fluid","background_color":"","content_liquid":"{% if collection.description != blank %}\n<hr>\n      <div class=\"collection-description grid__item rte\">\n        {{ collection.description }}\n      <\/div>\n    {% endif %}","padding_top":0,"padding_bottom":0,"reset_spacing":false}},"47b4aaae-a5a7-401b-a79c-d7b0652caf69":{"type":"custom-liquid","disabled":true,"settings":{"heading":"","description":"","text_alignment":"text-center","container":"container","background_color":"","content_liquid":"{% assign second_parameter = request.path | split:'\/'  %}\n\n              {% if second_parameter[1] ==\"collections\" and  second_parameter[2]  contains \"pipe-lighting-accessories\" %} \n<style>\n#CollectionSidebar{\ndisplay:none!important;}\n<\/style>\n {% else %}\n\n {% endif %}","padding_top":0,"padding_bottom":0,"reset_spacing":false}},"divider_PhNww8":{"type":"divider","settings":{"container":"container","border_height":3,"border_color":"#ebebeb","padding_top":0,"padding_bottom":0,"reset_spacing":false}},"custom_text_qedYj9":{"type":"custom-text","blocks":{"heading_R87WVJ":{"type":"heading","settings":{"heading":"Living Room Lighting Ideas: A Guide to Brighten Your Space","heading_color":"","heading_fs":40,"heading_fw":500,"heading_tf":"unset","heading_mt":14,"heading_mb":0}}},"block_order":["heading_R87WVJ"],"settings":{"container":"container","text_align":"text-center","bg_color":"","custom_class":"","padding_top":0,"padding_bottom":0,"reset_spacing":false}},"banner_image_bUhTqD":{"type":"banner-image","blocks":{"image_banner_DAU4XK":{"type":"image_banner","settings":{"banner_type":"image","banner_width":"12","image":"shopify:\/\/shop_images\/1_3_c8dd565b-8e67-4210-86d3-d15097b72c19.jpg","background_color":"","video_options":"local","video_url":"","link":"https:\/\/ledsone.co.uk\/collections\/living-or-dining-room-lighting","color":"default","content_spacing":"default","text_size":"medium","h_text_weight":400,"title":"","subtext":"","content":"","button_type":"primary","btn_content":"","open_link":"_blank"}}},"block_order":["image_banner_DAU4XK"],"settings":{"show_heading_header":false,"heading":"LED MODULE","description":"","text_alignment":"text-center","container":"container-fluid","banner_background_color":"","hover_effect":"translate-to-top","design_banner":"text-overlay-image","text_position":"center","text_align":"text-left","content_on_mobile":false,"column_gap":0,"padding_top":0,"padding_bottom":0,"reset_spacing":false}},"custom_liquid_BPkHwA":{"type":"custom-liquid","settings":{"heading":"","description":"","text_alignment":"text-left","container":"container","background_color":"","content_liquid":"<span id=\"docs-internal-guid-cd078599-7fff-c223-3f4f-639e4da6a9f4\"><p dir=\"ltr\" style=\"line-height: 1.38; margin-bottom: 12pt; margin-top: 12pt;\"><span style=\"font-family: Arial, sans-serif; font-size: 11pt; font-variant-alternates: normal; font-variant-east-asian: normal; font-variant-emoji: normal; font-variant-numeric: normal; font-variant-position: normal; vertical-align: baseline; white-space-collapse: preserve;\">Lighting is a critical aspect of interior design, especially in living rooms where ambiance, functionality, and style come together. The right lighting can transform your space into a cozy retreat or a lively hub for entertaining guests. In this guide, we’ll explore living room lighting ideas, trends, and tips to help you make informed choices for your home.<\/span><\/p><p dir=\"ltr\" style=\"line-height: 1.38; margin-bottom: 0pt; margin-top: 0pt;\"><\/p><hr \/><p><\/p><h3 dir=\"ltr\" style=\"line-height: 1.38; margin-bottom: 4pt; margin-top: 14pt;\"><span style=\"font-family: Arial, sans-serif; font-size: 13pt; font-variant-alternates: normal; font-variant-east-asian: normal; font-variant-emoji: normal; font-variant-numeric: normal; font-variant-position: normal; vertical-align: baseline; white-space-collapse: preserve;\">What Type of Lighting is Best for a Living Room?<\/span><\/h3><p dir=\"ltr\" style=\"line-height: 1.38; margin-bottom: 12pt; margin-top: 12pt;\"><span style=\"font-family: Arial, sans-serif; font-size: 11pt; font-variant-alternates: normal; font-variant-east-asian: normal; font-variant-emoji: normal; font-variant-numeric: normal; font-variant-position: normal; vertical-align: baseline; white-space-collapse: preserve;\">To achieve optimal lighting in a living room, it’s essential to layer three types of lighting:<\/span><\/p><h4 dir=\"ltr\" style=\"line-height: 1.38; margin-bottom: 2pt; margin-top: 12pt;\"><span style=\"font-family: Arial, sans-serif; font-size: 11pt; font-variant-alternates: normal; font-variant-east-asian: normal; font-variant-emoji: normal; font-variant-numeric: normal; font-variant-position: normal; vertical-align: baseline; white-space-collapse: preserve;\">1. Ambient Lighting<\/span><\/h4><p dir=\"ltr\" style=\"line-height: 1.38; margin-bottom: 12pt; margin-top: 12pt;\"><span style=\"font-family: Arial, sans-serif; font-size: 11pt; font-variant-alternates: normal; font-variant-east-asian: normal; font-variant-emoji: normal; font-variant-numeric: normal; font-variant-position: normal; vertical-align: baseline; white-space-collapse: preserve;\">Ambient lighting is the primary source of light in a living room. It provides an overall glow and sets the tone for the space.<\/span><\/p><ul style=\"margin-bottom: 0; margin-top: 0; padding-inline-start: 48px;\"><li aria-level=\"1\" dir=\"ltr\" style=\"font-family: Arial, sans-serif; font-size: 11pt; font-variant-alternates: normal; font-variant-east-asian: normal; font-variant-emoji: normal; font-variant-numeric: normal; font-variant-position: normal; list-style-type: disc; vertical-align: baseline; white-space: pre;\"><p dir=\"ltr\" role=\"presentation\" style=\"line-height: 1.38; margin-bottom: 0pt; margin-top: 12pt;\"><span style=\"font-size: 11pt; font-variant-alternates: normal; font-variant-east-asian: normal; font-variant-emoji: normal; font-variant-numeric: normal; font-variant-position: normal; font-weight: 700; text-wrap-mode: wrap; vertical-align: baseline;\">Options:<\/span><span style=\"font-size: 11pt; font-variant-alternates: normal; font-variant-east-asian: normal; font-variant-emoji: normal; font-variant-numeric: normal; font-variant-position: normal; text-wrap-mode: wrap; vertical-align: baseline;\"> Ceiling lights, living room ceiling lights, chandeliers, and recessed lights.<\/span><\/p><\/li><li aria-level=\"1\" dir=\"ltr\" style=\"font-family: Arial, sans-serif; font-size: 11pt; font-variant-alternates: normal; font-variant-east-asian: normal; font-variant-emoji: normal; font-variant-numeric: normal; font-variant-position: normal; list-style-type: disc; vertical-align: baseline; white-space: pre;\"><p dir=\"ltr\" role=\"presentation\" style=\"line-height: 1.38; margin-bottom: 12pt; margin-top: 0pt;\"><span style=\"font-size: 11pt; font-variant-alternates: normal; font-variant-east-asian: normal; font-variant-emoji: normal; font-variant-numeric: normal; font-variant-position: normal; font-weight: 700; text-wrap-mode: wrap; vertical-align: baseline;\">Suggestions:<\/span><span style=\"font-size: 11pt; font-variant-alternates: normal; font-variant-east-asian: normal; font-variant-emoji: normal; font-variant-numeric: normal; font-variant-position: normal; text-wrap-mode: wrap; vertical-align: baseline;\"> Consider modern ceiling lights for living rooms or LED ceiling light fixtures for energy efficiency and sleek designs.<\/span><\/p><\/li><\/ul><h4 dir=\"ltr\" style=\"line-height: 1.38; margin-bottom: 2pt; margin-top: 12pt;\"><span style=\"font-family: Arial, sans-serif; font-size: 11pt; font-variant-alternates: normal; font-variant-east-asian: normal; font-variant-emoji: normal; font-variant-numeric: normal; font-variant-position: normal; vertical-align: baseline; white-space-collapse: preserve;\">2. Task Lighting<\/span><\/h4><p dir=\"ltr\" style=\"line-height: 1.38; margin-bottom: 12pt; margin-top: 12pt;\"><span style=\"font-family: Arial, sans-serif; font-size: 11pt; font-variant-alternates: normal; font-variant-east-asian: normal; font-variant-emoji: normal; font-variant-numeric: normal; font-variant-position: normal; vertical-align: baseline; white-space-collapse: preserve;\">Task lighting focuses on specific activities like reading, working, or playing games.<\/span><\/p><ul style=\"margin-bottom: 0; margin-top: 0; padding-inline-start: 48px;\"><li aria-level=\"1\" dir=\"ltr\" style=\"font-family: Arial, sans-serif; font-size: 11pt; font-variant-alternates: normal; font-variant-east-asian: normal; font-variant-emoji: normal; font-variant-numeric: normal; font-variant-position: normal; list-style-type: disc; vertical-align: baseline; white-space: pre;\"><p dir=\"ltr\" role=\"presentation\" style=\"line-height: 1.38; margin-bottom: 0pt; margin-top: 12pt;\"><span style=\"font-size: 11pt; font-variant-alternates: normal; font-variant-east-asian: normal; font-variant-emoji: normal; font-variant-numeric: normal; font-variant-position: normal; font-weight: 700; text-wrap-mode: wrap; vertical-align: baseline;\">Options:<\/span><span style=\"font-size: 11pt; font-variant-alternates: normal; font-variant-east-asian: normal; font-variant-emoji: normal; font-variant-numeric: normal; font-variant-position: normal; text-wrap-mode: wrap; vertical-align: baseline;\"> Table lamps, adjustable floor lamps, and wall-mounted lights.<\/span><\/p><\/li><li aria-level=\"1\" dir=\"ltr\" style=\"font-family: Arial, sans-serif; font-size: 11pt; font-variant-alternates: normal; font-variant-east-asian: normal; font-variant-emoji: normal; font-variant-numeric: normal; font-variant-position: normal; list-style-type: disc; vertical-align: baseline; white-space: pre;\"><p dir=\"ltr\" role=\"presentation\" style=\"line-height: 1.38; margin-bottom: 12pt; margin-top: 0pt;\"><span style=\"font-size: 11pt; font-variant-alternates: normal; font-variant-east-asian: normal; font-variant-emoji: normal; font-variant-numeric: normal; font-variant-position: normal; font-weight: 700; text-wrap-mode: wrap; vertical-align: baseline;\">Suggestions:<\/span><span style=\"font-size: 11pt; font-variant-alternates: normal; font-variant-east-asian: normal; font-variant-emoji: normal; font-variant-numeric: normal; font-variant-position: normal; text-wrap-mode: wrap; vertical-align: baseline;\"> Place a floor lamp near your sofa or a reading nook to ensure adequate light for focused activities.<\/span><\/p><\/li><\/ul><h4 dir=\"ltr\" style=\"line-height: 1.38; margin-bottom: 2pt; margin-top: 12pt;\"><span style=\"font-family: Arial, sans-serif; font-size: 11pt; font-variant-alternates: normal; font-variant-east-asian: normal; font-variant-emoji: normal; font-variant-numeric: normal; font-variant-position: normal; vertical-align: baseline; white-space-collapse: preserve;\">3. Accent Lighting<\/span><\/h4><p dir=\"ltr\" style=\"line-height: 1.38; margin-bottom: 12pt; margin-top: 12pt;\"><span style=\"font-family: Arial, sans-serif; font-size: 11pt; font-variant-alternates: normal; font-variant-east-asian: normal; font-variant-emoji: normal; font-variant-numeric: normal; font-variant-position: normal; vertical-align: baseline; white-space-collapse: preserve;\">Accent lighting highlights architectural features, artwork, or decorative elements.<\/span><\/p><ul style=\"margin-bottom: 0; margin-top: 0; padding-inline-start: 48px;\"><li aria-level=\"1\" dir=\"ltr\" style=\"font-family: Arial, sans-serif; font-size: 11pt; font-variant-alternates: normal; font-variant-east-asian: normal; font-variant-emoji: normal; font-variant-numeric: normal; font-variant-position: normal; list-style-type: disc; vertical-align: baseline; white-space: pre;\"><p dir=\"ltr\" role=\"presentation\" style=\"line-height: 1.38; margin-bottom: 0pt; margin-top: 12pt;\"><span style=\"font-size: 11pt; font-variant-alternates: normal; font-variant-east-asian: normal; font-variant-emoji: normal; font-variant-numeric: normal; font-variant-position: normal; font-weight: 700; text-wrap-mode: wrap; vertical-align: baseline;\">Options:<\/span><span style=\"font-size: 11pt; font-variant-alternates: normal; font-variant-east-asian: normal; font-variant-emoji: normal; font-variant-numeric: normal; font-variant-position: normal; text-wrap-mode: wrap; vertical-align: baseline;\"> Wall lights, LED strips, and pendant lights.<\/span><\/p><\/li><li aria-level=\"1\" dir=\"ltr\" style=\"font-family: Arial, sans-serif; font-size: 11pt; font-variant-alternates: normal; font-variant-east-asian: normal; font-variant-emoji: normal; font-variant-numeric: normal; font-variant-position: normal; list-style-type: disc; vertical-align: baseline; white-space: pre;\"><p dir=\"ltr\" role=\"presentation\" style=\"line-height: 1.38; margin-bottom: 12pt; margin-top: 0pt;\"><span style=\"font-size: 11pt; font-variant-alternates: normal; font-variant-east-asian: normal; font-variant-emoji: normal; font-variant-numeric: normal; font-variant-position: normal; font-weight: 700; text-wrap-mode: wrap; vertical-align: baseline;\">Suggestions:<\/span><span style=\"font-size: 11pt; font-variant-alternates: normal; font-variant-east-asian: normal; font-variant-emoji: normal; font-variant-numeric: normal; font-variant-position: normal; text-wrap-mode: wrap; vertical-align: baseline;\"> Use pendant lights to add style and focus attention on coffee tables or seating areas.<\/span><\/p><\/li><\/ul><p dir=\"ltr\" style=\"line-height: 1.38; margin-bottom: 0pt; margin-top: 0pt;\"><\/p><hr \/><p><\/p><h3 dir=\"ltr\" style=\"line-height: 1.38; margin-bottom: 4pt; margin-top: 14pt;\"><span style=\"font-family: Arial, sans-serif; font-size: 13pt; font-variant-alternates: normal; font-variant-east-asian: normal; font-variant-emoji: normal; font-variant-numeric: normal; font-variant-position: normal; vertical-align: baseline; white-space-collapse: preserve;\">How to Create Good Lighting in a Living Room<\/span><\/h3><p dir=\"ltr\" style=\"line-height: 1.38; margin-bottom: 12pt; margin-top: 12pt;\"><span style=\"font-family: Arial, sans-serif; font-size: 11pt; font-variant-alternates: normal; font-variant-east-asian: normal; font-variant-emoji: normal; font-variant-numeric: normal; font-variant-position: normal; vertical-align: baseline; white-space-collapse: preserve;\">Creating a well-lit living room involves strategic placement and layering of lights. Here are some tips:<\/span><\/p><h4 dir=\"ltr\" style=\"line-height: 1.38; margin-bottom: 2pt; margin-top: 12pt;\"><span style=\"font-family: Arial, sans-serif; font-size: 11pt; font-variant-alternates: normal; font-variant-east-asian: normal; font-variant-emoji: normal; font-variant-numeric: normal; font-variant-position: normal; vertical-align: baseline; white-space-collapse: preserve;\">1. Layer Your Lighting<\/span><\/h4><p dir=\"ltr\" style=\"line-height: 1.38; margin-bottom: 12pt; margin-top: 12pt;\"><span style=\"font-family: Arial, sans-serif; font-size: 11pt; font-variant-alternates: normal; font-variant-east-asian: normal; font-variant-emoji: normal; font-variant-numeric: normal; font-variant-position: normal; vertical-align: baseline; white-space-collapse: preserve;\">Combine ambient, task, and accent lighting for a balanced look.<\/span><\/p><ul style=\"margin-bottom: 0; margin-top: 0; padding-inline-start: 48px;\"><li aria-level=\"1\" dir=\"ltr\" style=\"font-family: Arial, sans-serif; font-size: 11pt; font-variant-alternates: normal; font-variant-east-asian: normal; font-variant-emoji: normal; font-variant-numeric: normal; font-variant-position: normal; list-style-type: disc; vertical-align: baseline; white-space: pre;\"><p dir=\"ltr\" role=\"presentation\" style=\"line-height: 1.38; margin-bottom: 12pt; margin-top: 12pt;\"><span style=\"font-size: 11pt; font-variant-alternates: normal; font-variant-east-asian: normal; font-variant-emoji: normal; font-variant-numeric: normal; font-variant-position: normal; font-weight: 700; text-wrap-mode: wrap; vertical-align: baseline;\">Example:<\/span><span style=\"font-size: 11pt; font-variant-alternates: normal; font-variant-east-asian: normal; font-variant-emoji: normal; font-variant-numeric: normal; font-variant-position: normal; text-wrap-mode: wrap; vertical-align: baseline;\"> Pair a modern ceiling light fixture with wall-mounted sconces and a statement table lamp.<\/span><\/p><\/li><\/ul><h4 dir=\"ltr\" style=\"line-height: 1.38; margin-bottom: 2pt; margin-top: 12pt;\"><span style=\"font-family: Arial, sans-serif; font-size: 11pt; font-variant-alternates: normal; font-variant-east-asian: normal; font-variant-emoji: normal; font-variant-numeric: normal; font-variant-position: normal; vertical-align: baseline; white-space-collapse: preserve;\">2. Use Dimmers<\/span><\/h4><p dir=\"ltr\" style=\"line-height: 1.38; margin-bottom: 12pt; margin-top: 12pt;\"><span style=\"font-family: Arial, sans-serif; font-size: 11pt; font-variant-alternates: normal; font-variant-east-asian: normal; font-variant-emoji: normal; font-variant-numeric: normal; font-variant-position: normal; vertical-align: baseline; white-space-collapse: preserve;\">Dimmers allow you to adjust the light intensity, making the space versatile for various activities.<\/span><\/p><ul style=\"margin-bottom: 0; margin-top: 0; padding-inline-start: 48px;\"><li aria-level=\"1\" dir=\"ltr\" style=\"font-family: Arial, sans-serif; font-size: 11pt; font-variant-alternates: normal; font-variant-east-asian: normal; font-variant-emoji: normal; font-variant-numeric: normal; font-variant-position: normal; list-style-type: disc; vertical-align: baseline; white-space: pre;\"><p dir=\"ltr\" role=\"presentation\" style=\"line-height: 1.38; margin-bottom: 12pt; margin-top: 12pt;\"><span style=\"font-size: 11pt; font-variant-alternates: normal; font-variant-east-asian: normal; font-variant-emoji: normal; font-variant-numeric: normal; font-variant-position: normal; font-weight: 700; text-wrap-mode: wrap; vertical-align: baseline;\">Tip:<\/span><span style=\"font-size: 11pt; font-variant-alternates: normal; font-variant-east-asian: normal; font-variant-emoji: normal; font-variant-numeric: normal; font-variant-position: normal; text-wrap-mode: wrap; vertical-align: baseline;\"> Install dimmable ceiling lights in the living room for versatile lighting—bright for gatherings, and soft for relaxation.<\/span><\/p><\/li><\/ul><h4 dir=\"ltr\" style=\"line-height: 1.38; margin-bottom: 2pt; margin-top: 12pt;\"><span style=\"font-family: Arial, sans-serif; font-size: 11pt; font-variant-alternates: normal; font-variant-east-asian: normal; font-variant-emoji: normal; font-variant-numeric: normal; font-variant-position: normal; vertical-align: baseline; white-space-collapse: preserve;\">3. Optimize Placement<\/span><\/h4><p dir=\"ltr\" style=\"line-height: 1.38; margin-bottom: 12pt; margin-top: 12pt;\"><span style=\"font-family: Arial, sans-serif; font-size: 11pt; font-variant-alternates: normal; font-variant-east-asian: normal; font-variant-emoji: normal; font-variant-numeric: normal; font-variant-position: normal; vertical-align: baseline; white-space-collapse: preserve;\">Position lights to eliminate dark corners and ensure even distribution of light.<\/span><\/p><ul style=\"margin-bottom: 0; margin-top: 0; padding-inline-start: 48px;\"><li aria-level=\"1\" dir=\"ltr\" style=\"font-family: Arial, sans-serif; font-size: 11pt; font-variant-alternates: normal; font-variant-east-asian: normal; font-variant-emoji: normal; font-variant-numeric: normal; font-variant-position: normal; list-style-type: disc; vertical-align: baseline; white-space: pre;\"><p dir=\"ltr\" role=\"presentation\" style=\"line-height: 1.38; margin-bottom: 12pt; margin-top: 12pt;\"><span style=\"font-size: 11pt; font-variant-alternates: normal; font-variant-east-asian: normal; font-variant-emoji: normal; font-variant-numeric: normal; font-variant-position: normal; font-weight: 700; text-wrap-mode: wrap; vertical-align: baseline;\">Example:<\/span><span style=\"font-size: 11pt; font-variant-alternates: normal; font-variant-east-asian: normal; font-variant-emoji: normal; font-variant-numeric: normal; font-variant-position: normal; text-wrap-mode: wrap; vertical-align: baseline;\"> Use ceiling lighting to illuminate the center of the room and wall lights for peripheral areas.<\/span><\/p><\/li><\/ul><p dir=\"ltr\" style=\"line-height: 1.38; margin-bottom: 0pt; margin-top: 0pt;\"><\/p><hr \/><br \/><p><\/p><\/span>","padding_top":0,"padding_bottom":0,"reset_spacing":false}},"gallery_rdw6wK":{"type":"gallery","blocks":{"image_cUH9nh":{"type":"image","settings":{"image":"shopify:\/\/shop_images\/Pack4_20Vintage_20Industrial_20Ceiling_20Pendant_20Light_20Retro_20Loft_20Style_20Metal_20Shade_20Lamp0.webp","link":"https:\/\/ledsone.co.uk\/products\/4-pack-vintage-industrial-ceiling-pendant-light-retro-loft-style-metal-shade-lamp"}},"image_EhzQ9W":{"type":"image","settings":{"image":"shopify:\/\/shop_images\/3Pack-Ceiling_20Pendant_20Metal_20Shades_20Retro_20Design_20Light_20Hanging_20Home_20Lounge_20Lighting6.webp","link":"https:\/\/ledsone.co.uk\/products\/3-pack-ceiling-pendant-metal-shades-retro-design-light-hanging-home-lounge-lighting"}},"image_g4bh4R":{"type":"image","settings":{"image":"shopify:\/\/shop_images\/led_rope_lights_indoor_fec47064-f50a-4a77-b043-13a62996f256.jpg","link":"https:\/\/ledsone.co.uk\/products\/vintage-hemp-rope-e27-base-swan-neck-wall-light-4550"}},"image_YxfheC":{"type":"image","settings":{"image":"shopify:\/\/shop_images\/3b8877e7-542e-44d4-8e23-15d0a208244e.webp","link":"https:\/\/ledsone.co.uk\/products\/vintage-ceiling-shade-industrial-chandelier-light-retro-lamp-uk"}},"image_7JTW8z":{"type":"image","settings":{"image":"shopify:\/\/shop_images\/ColourPendantLampShade_10.webp","link":"https:\/\/ledsone.co.uk\/products\/yellow-colour-retro-style-metal-ceiling-hanging-pendant-light-shade-modern-design"}},"image_nyF6Eg":{"type":"image","settings":{"image":"shopify:\/\/shop_images\/ModernRetroSteproundRusticRedcagependantlightroundceilingbase_4036_2_17006efa-4b44-4855-a76d-02040b1ae095.webp","link":"https:\/\/ledsone.co.uk\/products\/modern-retro-step-round-rustic-red-cage-pendant-light-round-ceiling-base"}}},"block_order":["image_cUH9nh","image_EhzQ9W","image_g4bh4R","image_YxfheC","image_7JTW8z","image_nyF6Eg"],"settings":{"heading":"Lighting Your Living Room: A Collection of Stunning Designs","description":"","text_align":"text-center","container":"container","background_color":"","layout_type":"carousel","column_gap":30,"aspect_ratio":"original","custom_ratio":"21:9","actions_click":"unset","custom_column":3,"grid_image_desktop":4,"autoplay":true,"loop":true,"show_arrow":false,"show_bullet":true,"show_bullet_mobile":false,"padding_top":0,"padding_bottom":0,"reset_spacing":false}},"custom_liquid_NKDQi4":{"type":"custom-liquid","settings":{"heading":"","description":"","text_alignment":"text-center","container":"container","background_color":"","content_liquid":"<span id=\"docs-internal-guid-678b21b3-7fff-8c7a-b1de-e9256c208d3d\">\n        <h3 dir=\"ltr\">What are the Trends in Lighting for 2025?<\/h3>\n        <h4 dir=\"ltr\">1. Energy efficiency<\/h4>\n        <p dir=\"ltr\">Eco-friendly lighting options are in high demand. LED modules are popular for their energy efficiency and long lifespan.<\/p>\n        <ul>\n            <li><strong>Ledsone’s Contribution:<\/strong> Explore our range of LED products that blend style with eco-friendliness.<\/li>\n        <\/ul>\n        <h4 dir=\"ltr\">2. Minimalist Designs<\/h4>\n        <p dir=\"ltr\">Sleek and simple lighting fixtures are dominating trends.<\/p>\n        <ul>\n            <li><strong>Examples:<\/strong> Modern ceiling lights for living rooms with matte finishes in black, brass, or white.<\/li>\n        <\/ul>\n        <h4 dir=\"ltr\">3. Smart Lighting<\/h4>\n        <p dir=\"ltr\">Smart lighting systems offer convenience and personalization through apps or voice control.<\/p>\n        <ul>\n            <li><strong>Suggestions:<\/strong> Choose smart living room light fittings for enhanced functionality and control.<\/li>\n        <\/ul>\n        <h4 dir=\"ltr\">4. Layered Ceiling Lighting<\/h4>\n        <p dir=\"ltr\">Combining recessed lights, pendant lights, and chandeliers adds depth and dimension to your living room.<\/p>\n        <hr>\n        <h3 dir=\"ltr\">How Can I Light My Living Room Without Overhead Lights?<\/h3>\n        <p dir=\"ltr\">If your living room lacks overhead lighting, you can still achieve excellent lighting:<\/p>\n        <h4 dir=\"ltr\">1. Floor Lamps<\/h4>\n        <p dir=\"ltr\">Tall and elegant floor lamps provide ample ambient lighting.<\/p>\n        <ul>\n            <li><strong>Example:<\/strong> Place an arc floor lamp in the corner to light up the seating area.<\/li>\n        <\/ul>\n        <h4 dir=\"ltr\">2. Wall Lights<\/h4>\n        <p dir=\"ltr\">Mounted wall lights create a cozy atmosphere while saving space.<\/p>\n        <ul>\n            <li><strong>Options:<\/strong> Adjustable wall sconces or decorative fixtures.<\/li>\n        <\/ul>\n        <h4 dir=\"ltr\">3. Table Lamps<\/h4>\n        <p dir=\"ltr\">Table lamps are both functional and decorative.<\/p>\n        <ul>\n            <li><strong>Tip:<\/strong> Use lamps with patterned shades to add visual interest.<\/li>\n        <\/ul>\n        <h4 dir=\"ltr\">4. LED Strips<\/h4>\n        <p dir=\"ltr\">LED strips offer a modern touch when placed under shelves, furniture, or along walls.<\/p>\n        <ul>\n            <li><strong>Suggestion:<\/strong> Pair LED strips with dimmers for adjustable mood lighting.<\/li>\n        <\/ul>\n        <hr>\n        <h3 dir=\"ltr\">Lighting Ideas for Living Rooms<\/h3>\n        <h4 dir=\"ltr\">1. Ceiling Lamps for Living Rooms<\/h4>\n        <p dir=\"ltr\">Choose ceiling lamps that complement your living room’s decor.<\/p>\n        <ul>\n            <li><strong>Examples:<\/strong> Statement chandeliers, flush-mounted fixtures, or modern ceiling light fittings.<\/li>\n        <\/ul>\n        <h4 dir=\"ltr\">2. Living Room Ceiling Lighting Ideas<\/h4>\n        <p dir=\"ltr\">Experiment with a mix of recessed lights and pendant lights for a dynamic look.<\/p>\n        <ul>\n            <li><strong>Tip:<\/strong> Use ceiling lighting to create focal points in your living room.<\/li>\n        <\/ul>\n        <h4 dir=\"ltr\">3. Living Room Modern Ceiling Lights<\/h4>\n        <p dir=\"ltr\">Modern designs bring sophistication and functionality to your space.<\/p>\n        <ul>\n            <li><strong>Options:<\/strong> Opt for sleek, geometric ceiling light fixtures in metallic finishes.<\/li>\n        <\/ul>\n        <h4 dir=\"ltr\">4. Lighting for Small Living Rooms<\/h4>\n        <p dir=\"ltr\">Maximize light in compact spaces with clever solutions.<\/p>\n        <ul>\n            <li><strong>Suggestions:<\/strong> Use mirrors to reflect light and choose compact yet powerful ceiling light fixtures.<\/li>\n        <\/ul>\n    <\/span>","padding_top":0,"padding_bottom":0,"reset_spacing":false}},"gallery_aFQW4d":{"type":"gallery","blocks":{"image_renDfq":{"type":"image","settings":{"image":"shopify:\/\/shop_images\/PLTYBC_WCBNBC_ICST64E2740.webp","link":"https:\/\/ledsone.co.uk\/products\/industrial-table-lamp"}},"image_dmxDrd":{"type":"image","settings":{"image":"shopify:\/\/shop_images\/Modern_Ceramic_Base_Table_Lamp_28df827e-e6e2-4419-9c9e-02f71cd0e9f2.webp","link":"https:\/\/ledsone.co.uk\/products\/industrial-table-lamp"}},"image_9bg8Bz":{"type":"image","settings":{"image":"shopify:\/\/shop_images\/09_5_2a33c0c7-ce8a-4f45-929c-8f44f249fb4d.webp","link":"https:\/\/ledsone.co.uk\/products\/desk-lamp-wood-bedside-table-lamp-plugin-light"}},"image_A4MV6U":{"type":"image","settings":{"image":"shopify:\/\/shop_images\/o_dUWfHrN2eb.webp","link":"https:\/\/ledsone.co.uk\/products\/colorful-mosaic-lamp-for-uk"}}},"block_order":["image_renDfq","image_dmxDrd","image_9bg8Bz","image_A4MV6U"],"disabled":true,"settings":{"heading":"Transform Your Space with Beautiful Table Lamps","description":"","text_align":"text-center","container":"container","background_color":"","layout_type":"carousel","column_gap":30,"aspect_ratio":"original","custom_ratio":"21:9","actions_click":"unset","custom_column":3,"grid_image_desktop":4,"autoplay":false,"loop":false,"show_arrow":false,"show_bullet":true,"show_bullet_mobile":false,"padding_top":0,"padding_bottom":0,"reset_spacing":false}},"custom_liquid_CAHxTN":{"type":"custom-liquid","settings":{"heading":"","description":"","text_alignment":"text-center","container":"container","background_color":"","content_liquid":"<span id=\"docs-internal-guid-678b21b3-7fff-8c7a-b1de-e9256c208d3d\">\n        <h3 dir=\"ltr\">Final Tips for Choosing Lights for Your Living Room<\/h3>\n        <h4 dir=\"ltr\">1. Consider Your Room’s Size<\/h4>\n        <p dir=\"ltr\">Pick lighting proportional to your living room’s dimensions.<\/p>\n        <ul>\n            <li><strong>Example:<\/strong> A large chandelier might overwhelm a small room, but flush-mounted ceiling lights work perfectly.<\/li>\n        <\/ul>\n        <h4 dir=\"ltr\">2. Match Your Décor Style<\/h4>\n        <p dir=\"ltr\">Your lighting should complement the overall design of your living room.<\/p>\n        <ul>\n            <li><strong>Tip:<\/strong> Modern ceiling lights for living rooms are ideal for contemporary spaces.<\/li>\n        <\/ul>\n        <h4 dir=\"ltr\">3. Prioritize Energy Efficiency<\/h4>\n        <p dir=\"ltr\">LED lights save energy and last longer, making them a smart choice.<\/p>\n        <ul>\n            <li><strong>Ledsone’s Range:<\/strong> Explore our collection of energy-efficient LED modules and light fittings.<\/li>\n        <\/ul>\n        <hr>\n        <h3 dir=\"ltr\">Conclusion<\/h3>\n        <p dir=\"ltr\">Proper lighting can elevate your living room’s ambiance and functionality. By layering ambient, task, and accent lighting, you can create a space that’s both inviting and stylish. Embrace trends like minimalist designs, smart lighting, and eco-friendliness to keep your living room modern and energy-efficient.<\/p>\n        <p dir=\"ltr\">Ledsone offers pendant lights, wall lights, and LED modules to create your ideal living room lighting. Explore our living room lighting collection to find the perfect fit for your home!<\/p>\n    <\/span>","padding_top":0,"padding_bottom":0,"reset_spacing":false}}},"order":["divider_8BUdXc","main-collection-heading","8498460c-0376-40d1-bafc-199edbe0edfc","439e38df-206c-40a8-9cd5-fc0e5f00f9d3","product-grid","b1a1633c-9de0-43c8-8a60-a0eddc69dfb1","47b4aaae-a5a7-401b-a79c-d7b0652caf69","divider_PhNww8","custom_text_qedYj9","banner_image_bUhTqD","custom_liquid_BPkHwA","gallery_rdw6wK","custom_liquid_NKDQi4","gallery_aFQW4d","custom_liquid_CAHxTN"]}