{"sections":{"38f3b02d-4d55-4285-bac3-806855394e6d":{"type":"scrolling-text","blocks":{"template--16815349170426__38f3b02d-4d55-4285-bac3-806855394e6d-1689674622b7aed419-0":{"type":"scrolling_text","disabled":true,"settings":{"content":"<p>FREE DELIVERY ORDER OVER £25<\/p>","text_link":""}}},"block_order":["template--16815349170426__38f3b02d-4d55-4285-bac3-806855394e6d-1689674622b7aed419-0"],"disabled":true,"settings":{"container":"container","background_color":"#364a9b","s_text_color":"#ffffff","text_font_size":12,"text_font_weight":500,"text_time":25,"text_spacing":50,"spacing_icon":"icon_line","padding_top":0,"padding_bottom":0,"reset_spacing":false}},"main-collection-heading":{"type":"main-collection-heading","blocks":{"f06a38ad-a426-42c0-a5ff-48ae0218618e":{"type":"1","settings":{"text_cl":"#111111","text_fs":30}}},"block_order":["f06a38ad-a426-42c0-a5ff-48ae0218618e"],"settings":{"layout":"full-width","background_heading_color":"rgba(0,0,0,0)","breadcrumb_color":"#111111","show_banner":false,"use_collection_image":false,"min_height":265,"parallax":false,"show_overlay":true,"overlay":51,"design":"text-overlay-image","text_postion":"text-center"}},"custom_html_EigtzR":{"type":"custom-html","name":"Custom HTML","settings":{"heading":"","description":"","text_alignment":"text-center","container":"container","background_color":"","content_html":"<div class=\"container\">\n  <div class=\"promo-banner blue-transparent-ui\">\n    <div class=\"promo-text\">\n      <span class=\"discount\">Get 10% Off<\/span>\n      <span class=\"offer\">Buy 2 Pendant Lights<\/span>\n    <\/div>\n    <div class=\"promo-code\" onclick=\"copyCode()\">\n      <span id=\"code-label\">Copy Code:<\/span>\n      <span id=\"code-text\">HLIGHT10<\/span>\n      <span class=\"copy-tooltip\" id=\"copy-tooltip\">Copied!<\/span>\n    <\/div>\n  <\/div>\n<\/div>\n\n<style>\n\/* ── FIX: was fixed 1400px — now fluid ── *\/\n.container {\n  width: 100%;\n  max-width: 1400px;\n  margin: 0 auto;\n  padding: 0 20px;\n  box-sizing: border-box;\n}\n\n.promo-banner {\n  display: flex;\n  justify-content: center;\n  align-items: center;\n  text-align: center;\n  padding: 18px 25px;\n  border-radius: 16px;\n  font-family: -apple-system, BlinkMacSystemFont, 'Segoe UI', Roboto, Oxygen, Ubuntu, sans-serif;\n  flex-wrap: wrap;\n  gap: 18px;\n  backdrop-filter: blur(12px);\n  transition: all 0.4s cubic-bezier(0.4, 0, 0.2, 1);\n  position: relative;\n  overflow: hidden;\n  box-sizing: border-box;\n}\n\n.promo-banner.blue-transparent-ui {\n  background: linear-gradient(135deg,\n    rgba(150, 150, 150, 0.15) 0%,\n    rgba(120, 120, 120, 0.2) 100%);\n  border: 1px solid rgba(255, 255, 255, 0.25);\n  box-shadow:\n    0 8px 32px rgba(120, 120, 120, 0.3),\n    0 1px 0 rgba(255, 255, 255, 0.15) inset,\n    0 -1px 0 rgba(0, 0, 0, 0.1) inset;\n}\n\n.promo-banner.blue-transparent-ui::before {\n  content: '';\n  position: absolute;\n  top: 0;\n  left: -100%;\n  width: 100%;\n  height: 100%;\n  background: linear-gradient(90deg,\n    transparent,\n    rgba(255, 255, 255, 0.1),\n    transparent);\n  transition: left 0.7s ease;\n  z-index: 1;\n}\n\n.promo-banner.blue-transparent-ui:hover::before { left: 100%; }\n\n.promo-banner.blue-transparent-ui:hover {\n  background: linear-gradient(135deg,\n    rgba(150, 150, 150, 0.25) 0%,\n    rgba(120, 120, 120, 0.3) 100%);\n  box-shadow:\n    0 12px 40px rgba(120, 120, 120, 0.4),\n    0 2px 0 rgba(255, 255, 255, 0.2) inset,\n    0 -1px 0 rgba(0, 0, 0, 0.15) inset;\n  border-color: rgba(255, 255, 255, 0.35);\n  transform: translateY(-2px);\n}\n\n.promo-text {\n  display: flex;\n  flex-direction: column;\n  font-size: 15px;\n  font-weight: 500;\n  color: rgba(22, 6, 6, 0.98);\n  text-shadow: 0 2px 4px rgba(0, 0, 0, 0.2);\n  position: relative;\n  z-index: 2;\n}\n\n.promo-text .discount {\n  font-size: 20px;\n  font-weight: 700;\n  color: #000000;\n  text-shadow: 0 2px 4px rgba(255, 255, 255, 0.5);\n  letter-spacing: -0.02em;\n}\n\n.promo-text .offer {\n  color: #000000;\n  font-size: 14px;\n  margin-top: 4px;\n  font-weight: 500;\n}\n\n.promo-code {\n  background: linear-gradient(135deg,\n    rgba(140, 140, 140, 0.5) 0%,\n    rgba(110, 110, 110, 0.6) 100%);\n  color: #070303;\n  padding: 12px 24px;\n  border-radius: 10px;\n  cursor: pointer;\n  font-weight: 600;\n  position: relative;\n  transition: all 0.3s cubic-bezier(0.4, 0, 0.2, 1);\n  border: 1px solid rgba(255, 255, 255, 0.3);\n  backdrop-filter: blur(10px);\n  box-shadow:\n    0 4px 15px rgba(120, 120, 120, 0.4),\n    0 1px 0 rgba(255, 255, 255, 0.2) inset,\n    0 -1px 0 rgba(50, 50, 50, 0.4) inset;\n  z-index: 2;\n  min-width: 180px;\n  display: flex;\n  justify-content: center;\n  align-items: center;\n  gap: 8px;\n  box-sizing: border-box;\n}\n\n.promo-code:hover {\n  background: linear-gradient(135deg,\n    rgba(150, 150, 150, 0.6) 0%,\n    rgba(120, 120, 120, 0.7) 100%);\n  transform: translateY(-2px) scale(1.02);\n  box-shadow:\n    0 8px 25px rgba(120, 120, 120, 0.5),\n    0 2px 0 rgba(255, 255, 255, 0.25) inset,\n    0 -1px 0 rgba(50, 50, 50, 0.5) inset;\n  border-color: rgba(255, 255, 255, 0.4);\n}\n\n.promo-code:active {\n  transform: translateY(0) scale(1);\n  transition: transform 0.1s;\n  box-shadow: 0 2px 10px rgba(120, 120, 120, 0.4), 0 1px 0 rgba(255, 255, 255, 0.1) inset;\n}\n\n.copy-tooltip {\n  position: absolute;\n  top: 20px;\n  left: 50%;\n  transform: translateX(-50%) translateY(5px) scale(0.95);\n  background: linear-gradient(135deg,\n    rgba(140, 140, 140, 0.95) 0%,\n    rgba(110, 110, 110, 0.95) 100%);\n  color: #fff;\n  font-size: 13px;\n  padding: 10px 16px;\n  border-radius: 8px;\n  opacity: 0;\n  pointer-events: none;\n  transition: all 0.3s cubic-bezier(0.34, 1.56, 0.64, 1);\n  backdrop-filter: blur(10px);\n  border: 1px solid rgba(255, 255, 255, 0.2);\n  white-space: nowrap;\n  box-shadow: 0 4px 20px rgba(120, 120, 120, 0.5);\n  z-index: 100;\n}\n\n.copy-tooltip::after {\n  content: '';\n  position: absolute;\n  bottom: -6px;\n  left: 50%;\n  transform: translateX(-50%);\n  border-left: 7px solid transparent;\n  border-right: 7px solid transparent;\n  border-top: 7px solid rgba(140, 140, 140, 0.95);\n}\n\n.promo-code #code-label {\n  font-weight: 500;\n  opacity: 0.95;\n  color: rgba(14, 7, 7, 0.95);\n  font-size: 14px;\n}\n\n.promo-code #code-text {\n  color: rgb(19, 10, 10);\n  font-weight: 700;\n  letter-spacing: 1px;\n  text-shadow: 0 2px 4px rgba(0, 0, 0, 0.3);\n  font-size: 16px;\n  background: linear-gradient(135deg, #ffffff 0%, #cce5ff 100%);\n  -webkit-background-clip: text;\n  -webkit-text-fill-color: transparent;\n  background-clip: text;\n  padding: 2px 6px;\n  border-radius: 4px;\n  background-color: rgba(255, 255, 255, 0.1);\n}\n\n.promo-code:focus-visible {\n  outline: 2px solid rgba(150, 150, 150, 0.8);\n  outline-offset: 2px;\n  box-shadow: 0 0 0 3px rgba(150, 150, 150, 0.2), 0 8px 25px rgba(120, 120, 120, 0.5);\n}\n\n\/* ── TABLET: 768px ── *\/\n@media (max-width: 768px) {\n  .container { padding: 0 16px; }\n\n  .promo-banner {\n    gap: 14px;\n    padding: 16px 20px;\n  }\n\n  .promo-text .discount { font-size: 18px; }\n  .promo-text .offer    { font-size: 13px; }\n\n  .promo-code {\n    min-width: 160px;\n    padding: 10px 20px;\n  }\n\n  .promo-code #code-label { font-size: 13px; }\n  .promo-code #code-text  { font-size: 15px; }\n}\n\n\/* ── MOBILE: 600px ── *\/\n@media (max-width: 600px) {\n  .container { padding: 0 12px; }\n\n  .promo-banner {\n    flex-direction: column;\n    text-align: center;\n    padding: 20px 16px;\n    gap: 14px;\n    border-radius: 14px;\n    backdrop-filter: blur(20px);\n  }\n\n  .promo-text .discount { font-size: 18px; }\n  .promo-text .offer    { font-size: 13px; margin-top: 3px; }\n\n  .promo-code {\n    width: 100%;\n    max-width: 100%;\n    min-width: unset;\n    padding: 12px 16px;\n    justify-content: center;\n    box-sizing: border-box;\n  }\n\n  .promo-code #code-label { font-size: 13px; }\n  .promo-code #code-text  { font-size: 15px; }\n\n  \/* Tooltip above the button on mobile *\/\n  .copy-tooltip {\n    top: auto;\n    bottom: calc(100% + 10px);\n    font-size: 12px;\n    padding: 8px 14px;\n  }\n\n  .copy-tooltip::after {\n    top: 100%;\n    bottom: auto;\n    border-top: none;\n    border-bottom: 7px solid rgba(140, 140, 140, 0.95);\n    border-left: 7px solid transparent;\n    border-right: 7px solid transparent;\n  }\n}\n\n\/* ── SMALL MOBILE: 380px ── *\/\n@media (max-width: 380px) {\n  .container { padding: 0 8px; }\n\n  .promo-banner { padding: 16px 12px; gap: 12px; border-radius: 12px; }\n\n  .promo-text .discount { font-size: 16px; }\n  .promo-text .offer    { font-size: 12px; }\n\n  .promo-code { padding: 10px 14px; }\n  .promo-code #code-label { font-size: 12px; }\n  .promo-code #code-text  { font-size: 14px; }\n}\n\n@media (prefers-color-scheme: dark) {\n  .promo-banner.blue-transparent-ui {\n    background: linear-gradient(135deg,\n      rgba(140, 140, 140, 0.2) 0%,\n      rgba(110, 110, 110, 0.25) 100%);\n    box-shadow: 0 8px 32px rgba(120, 120, 120, 0.35), 0 1px 0 rgba(255, 255, 255, 0.1) inset;\n  }\n  .promo-text .discount {\n    color: #000000;\n    text-shadow: 0 2px 4px rgba(255, 255, 255, 0.6);\n  }\n}\n<\/style>\n\n<script>\nfunction copyCode() {\n  const codeText = document.getElementById(\"code-text\").innerText;\n  navigator.clipboard.writeText(codeText).then(() => {\n    showTooltip();\n  }).catch(() => {\n    const textArea = document.createElement('textarea');\n    textArea.value = codeText;\n    document.body.appendChild(textArea);\n    textArea.select();\n    document.execCommand('copy');\n    document.body.removeChild(textArea);\n    showTooltip();\n  });\n}\n\nfunction showTooltip() {\n  const tooltip = document.getElementById(\"copy-tooltip\");\n  tooltip.style.opacity = \"1\";\n  tooltip.style.transform = \"translateX(-50%) translateY(0) scale(1)\";\n  tooltip.animate([\n    { transform: 'translateX(-50%) translateY(0) scale(1)' },\n    { transform: 'translateX(-50%) translateY(-3px) scale(1.05)', offset: 0.3 },\n    { transform: 'translateX(-50%) translateY(0) scale(1)' }\n  ], { duration: 600, easing: 'cubic-bezier(0.34, 1.56, 0.64, 1)' });\n  setTimeout(() => {\n    tooltip.style.opacity = \"0\";\n    tooltip.style.transform = \"translateX(-50%) translateY(5px) scale(0.95)\";\n  }, 2000);\n}\n\nconst promoCodeEl = document.querySelector('.promo-code');\npromoCodeEl.setAttribute('tabindex', '0');\npromoCodeEl.addEventListener('keydown', (e) => {\n  if (e.key === 'Enter' || e.key === ' ') { e.preventDefault(); copyCode(); }\n});\n<\/script>","padding_top":0,"padding_bottom":0,"reset_spacing":false}},"8498460c-0376-40d1-bafc-199edbe0edfc":{"type":"collection-list","blocks":{"616f3472-abe6-41ef-8d49-4e190d1fc5cc":{"type":"collection_item","settings":{"title_collection":"Multi Outlet Pendant","collection":"spider-light","image":"shopify:\/\/shop_images\/pendant_light_spider.jpg"}},"36a53b4a-830c-4660-a410-d73343bf9d7d":{"type":"collection_item","settings":{"title_collection":"Pendant Holder","collection":"pendant-holder","image":"shopify:\/\/shop_images\/1128.jpg"}},"981b08cc-5195-40cd-b5f4-79c51acd6dbb":{"type":"collection_item","settings":{"title_collection":"Hemp Lighting","collection":"hemp-rope-lighting","image":"shopify:\/\/shop_images\/Hemprope.jpg"}},"template--16567751475447__8498460c-0376-40d1-bafc-199edbe0edfc-16665857567f9937b1-3":{"type":"collection_item","settings":{"title_collection":"Cage pendant light","collection":"cage-pendant-light","image":"shopify:\/\/shop_images\/home_Cage_lighting_6f17d2fc-b5ab-4da8-81b9-bfb668c813dc.png"}},"template--16567751475447__8498460c-0376-40d1-bafc-199edbe0edfc-16665857567f9937b1-0":{"type":"collection_item","settings":{"title_collection":"Glass Pendant lights","collection":"glass-pendant-lights","image":"shopify:\/\/shop_images\/Vintage_Lampshades_Amber_Glass_Ceiling_Pendant_Light.webp"}},"template--16567751475447__8498460c-0376-40d1-bafc-199edbe0edfc-16665857567f9937b1-1":{"type":"collection_item","settings":{"title_collection":"Tiffany Pendant Lights","collection":"tiffany-pendant-lights","image":"shopify:\/\/shop_images\/2_2_11zon_b36d83fb-d99c-4290-b390-95ca912046b0.jpg"}}},"block_order":["616f3472-abe6-41ef-8d49-4e190d1fc5cc","36a53b4a-830c-4660-a410-d73343bf9d7d","981b08cc-5195-40cd-b5f4-79c51acd6dbb","template--16567751475447__8498460c-0376-40d1-bafc-199edbe0edfc-16665857567f9937b1-3","template--16567751475447__8498460c-0376-40d1-bafc-199edbe0edfc-16665857567f9937b1-0","template--16567751475447__8498460c-0376-40d1-bafc-199edbe0edfc-16665857567f9937b1-1"],"settings":{"heading":"","description":"","text_alignment":"text-center","container":"container-fluid","background_color":"","design_layout":"carousel","design_collection":"design-4","hover_effect":"zoom","show_count_product":false,"custom_width_images":false,"width_image":200,"images_style":"square","image_ratio":"1\/1","custom_ratio":"21:9","custom_column":6,"column_gap":10,"autoplay":true,"loop":true,"show_arrow":true,"show_bullet":false,"show_bullet_mobile":false,"reveal_on_scroll":false,"padding_top":12,"padding_bottom":0,"reset_spacing":true}},"439e38df-206c-40a8-9cd5-fc0e5f00f9d3":{"type":"spacing","settings":{"spacing_desktop":30,"spacing_moible":10}},"custom_html_Eh7Kck":{"type":"custom-html","settings":{"heading":"","description":"","text_alignment":"text-center","container":"container","background_color":"","content_html":"<a href=\"https:\/\/ledsone.co.uk\/pages\/hanging-lights\" class=\"button-style\">\n  Information\n<\/a>\n\n<style>\n.button-style {\n  display: inline-block;\n  padding: 10px 15px;\n  background-color: #f0f0f0; \/* Button background color *\/\n  color: #111; \/* Text color *\/\n  font-weight: bold;\n  text-decoration: none; \/* Removes underline *\/\n  border: 1px solid #ddd; \/* Adds a border *\/\n  border-radius: 20px; \/* Rounded corners *\/\n  text-align: center; \/* Centers the text *\/\n  cursor: pointer; \/* Pointer cursor on hover *\/\n  transition: background-color 0.3s ease; \/* Smooth hover effect *\/\n}\n\n.button-style:hover {\n  background-color: #ddd; \/* Background color on hover *\/\n  color: #000; \/* Text color on hover *\/\n}\n.container {\n  text-align: right; \/* Aligns child elements to the right *\/\n<\/style>","padding_top":0,"padding_bottom":0,"reset_spacing":false}},"product-grid":{"type":"main-collection-product","blocks":{"35c81196-1f20-4b1d-98e4-1bea284fe6d7":{"type":"categories","disabled":true,"settings":{"title":"Category","menu":""}},"3b46edaf-55ef-46a8-b8fe-a6eb39ade3a8":{"type":"filter_by_dynamic","settings":{}},"cross_sell_collection_eaMec3":{"type":"cross_sell_collection","disabled":true,"settings":{"title":"You May Also Need","collection":"hooks-and-rings","limit_to_handles":"","limit":6,"columns":6,"show_view_all":true}},"2039056a-3cc3-4534-a522-d35bdfbaef6c":{"type":"popular_product","disabled":true,"settings":{"title":"Featured Product","collection":"best-offer","type_product":"list","maximum":3}},"8fe431f8-91f7-4b21-a605-4b55df7293e1":{"type":"image_banner","disabled":true,"settings":{"url":"","open_link":false}}},"block_order":["35c81196-1f20-4b1d-98e4-1bea284fe6d7","3b46edaf-55ef-46a8-b8fe-a6eb39ade3a8","cross_sell_collection_eaMec3","2039056a-3cc3-4534-a522-d35bdfbaef6c","8fe431f8-91f7-4b21-a605-4b55df7293e1"],"settings":{"layout":"container-fluid","enable_list_view":false,"products_column":6,"number_products_grid":24,"number_products_list":6,"pagination":"infinit_scrolling","product_page_count":true,"product_sort_options":true,"progress_bar":true,"enable_sidebar":true,"sidebar_position":"dropdonw_sidebar","variant_color":"Colour, couleur, Farbe, Kleur, Farge","variant_size":"Size, Dimensione, Taille","show_count":true}},"custom_liquid_z46zMY":{"type":"custom-liquid","settings":{"heading":"A Guide to Good Lighting: Creating Your Perfect Home Atmosphere","description":"","text_alignment":"text-center","container":"container","background_color":"","content_liquid":"","padding_top":0,"padding_bottom":0,"reset_spacing":false}},"custom_text_PYCWrA":{"type":"custom-text","blocks":{"desc_D8RVgc":{"type":"desc","settings":{"desc":"<p>Have you ever entered a room and felt instantly comfortable, but weren't sure why? The answer may lie in the lighting. Thoughtful lighting can make all the difference in creating a warm, inviting atmosphere. Whether you're a homeowner wanting to refresh your space or a renter looking for temporary fixes, mastering lighting can turn your home from ordinary to extraordinary.<\/p>","desc_color":"","desc_fs":18,"desc_fw":200,"content_width":100,"desc_tf":"unset","desc_mt":0,"desc_mb":0}}},"block_order":["desc_D8RVgc"],"settings":{"container":"container","text_align":"text-left","bg_color":"","custom_class":"","padding_top":0,"padding_bottom":0,"reset_spacing":false}},"banner_image_jQGMQz":{"type":"banner-image","blocks":{"image_banner_7Jpw4c":{"type":"image_banner","settings":{"banner_type":"image","banner_width":"12","image":"shopify:\/\/shop_images\/pendant_light_guid.jpg","background_color":"","video_options":"local","video_url":"https:\/\/www.youtube.com\/watch?v=_9VUPq3SxOc","link":"https:\/\/ledsone.co.uk\/collections\/kitchen-lights-for-over-table","color":"default","content_spacing":"default","text_size":"medium","h_text_weight":400,"title":"","subtext":"","content":"","button_type":"primary","btn_content":"","open_link":"_blank"}}},"block_order":["image_banner_7Jpw4c"],"settings":{"show_heading_header":false,"heading":"Title","description":"","text_alignment":"text-center","container":"container","banner_background_color":"","hover_effect":"zoom","design_banner":"text-overlay-image","text_position":"top","text_align":"text-left","content_on_mobile":false,"column_gap":30,"padding_top":0,"padding_bottom":0,"reset_spacing":false}},"custom_liquid_U4pApF":{"type":"custom-liquid","settings":{"heading":"Why Lighting Matters?","description":"","text_alignment":"text-left","container":"container","background_color":"","content_liquid":"","padding_top":0,"padding_bottom":0,"reset_spacing":false}},"custom_text_RUtjjR":{"type":"custom-text","blocks":{"desc_J6rtAn":{"type":"desc","settings":{"desc":"<p>Poor lighting isn't just about aesthetics – it can affect everything from your mood to your productivity. Many people struggle with harsh overhead lights that create an uninviting atmosphere, or insufficient lighting that makes daily tasks difficult. The good news? Creating the<a href=\"https:\/\/ledsone.co.uk\/\" target=\"_blank\" title=\"https:\/\/ledsone.co.uk\/\"> perfect lighting<\/a> scheme is both achievable and affordable, regardless of your living situation.<\/p>","desc_color":"","desc_fs":16,"desc_fw":200,"content_width":100,"desc_tf":"unset","desc_mt":0,"desc_mb":0}}},"block_order":["desc_J6rtAn"],"settings":{"container":"container","text_align":"text-left","bg_color":"","custom_class":"","padding_top":0,"padding_bottom":0,"reset_spacing":false}},"custom_liquid_KeeLkN":{"type":"custom-liquid","settings":{"heading":"Understanding Your Lighting Needs","description":"","text_alignment":"text-left","container":"container","background_color":"","content_liquid":"","padding_top":0,"padding_bottom":0,"reset_spacing":false}},"custom_text_CmcrEN":{"type":"custom-text","blocks":{"desc_m6WqzN":{"type":"desc","settings":{"desc":"<p>Before diving into specific solutions, consider the three main types of lighting every space needs:<\/p><ul><li><strong>Ambient Lighting:<\/strong> This provides overall illumination and usually comes from <a href=\"https:\/\/ledsone.co.uk\/collections\/ceiling-lights-for-flash-lights\" target=\"_blank\" title=\"Ceiling light \">ceiling fixtures<\/a>. Whether you're considering sleek<a href=\"https:\/\/ledsone.co.uk\/collections\/kitchen-lights-for-over-table\" target=\"_blank\" title=\"black pendant light\"> black ceiling lights for your kitchen<\/a> or contemporary pendant lighting for your living room, the key is choosing fixtures that complement your space while providing adequate brightness.<\/li><li><strong>Task Lighting: <\/strong>Essential for specific activities like reading, cooking, or working. Think under-cabinet lights in the kitchen or<a href=\"https:\/\/ledsone.co.uk\/collections\/table-lamps\" target=\"_blank\" title=\"table lamp\"> adjustable desk lamps<\/a> in your home office.<\/li><li><strong>Accent Lighting: <\/strong>The secret weapon of cozy spaces. Use <a href=\"https:\/\/ledsone.co.uk\/collections\/pendant-lights?page=39\" target=\"_blank\" title=\"pendant lighting\">pendant lamps<\/a>, <a href=\"https:\/\/ledsone.co.uk\/collections\/wall-light\" target=\"_blank\" title=\"new wall light\">wall sconces<\/a>, or strategically placed table lamps to create atmosphere and highlight architectural features.<\/li><\/ul>","desc_color":"","desc_fs":16,"desc_fw":400,"content_width":100,"desc_tf":"unset","desc_mt":0,"desc_mb":0}}},"block_order":["desc_m6WqzN"],"settings":{"container":"container","text_align":"text-left","bg_color":"","custom_class":"","padding_top":0,"padding_bottom":0,"reset_spacing":false}},"gallery_exLdca":{"type":"gallery","blocks":{"image_Lx7dcf":{"type":"image","settings":{"image":"shopify:\/\/shop_images\/Accent_Light.webp","link":"https:\/\/ledsone.co.uk\/products\/industrial-retro-loft-glass-3way-ceiling-lamp-shade-pendant-light-5607"}},"image_EkN3gh":{"type":"image","settings":{"image":"shopify:\/\/shop_images\/versatile_light.webp","link":"https:\/\/ledsone.co.uk\/products\/3-way-industrial-conduit-pipe-ceiling-pendant-diy-light-fixture"}},"image_xY7mTh":{"type":"image","settings":{"image":"shopify:\/\/shop_images\/black_ceiling_light.webp","link":"https:\/\/ledsone.co.uk\/products\/industrial-conduit-pipe-plug-in-wall-light-kit-e27-lamp-wall-mounted-5687"}},"image_dixmRf":{"type":"image","settings":{"image":"shopify:\/\/shop_images\/task_lighting.webp","link":"https:\/\/ledsone.co.uk\/products\/industrial-vintage-modern-metal-retro-e27-ceiling-red-barn-slotted-pendant-shade"}},"image_UezecW":{"type":"image","settings":{"image":"shopify:\/\/shop_images\/LENIER_LIGHTING_4269350a-4d6d-4d5b-9b97-daf0f7d0fc02.webp","link":"https:\/\/ledsone.co.uk\/products\/modern-linear-pendant-lighting-with-rectangle-clear-crystal-shade-5051"}},"image_LD7Gkh":{"type":"image","settings":{"image":"shopify:\/\/shop_images\/Accent_Lighting.webp","link":"https:\/\/ledsone.co.uk\/products\/turkish-mosaic-tiles-glass-pendant-light-fixture-globe-shape-4910"}}},"block_order":["image_Lx7dcf","image_EkN3gh","image_xY7mTh","image_dixmRf","image_UezecW","image_LD7Gkh"],"settings":{"heading":"","description":"","text_align":"text-center","container":"container","background_color":"","layout_type":"carousel","column_gap":30,"aspect_ratio":"original","custom_ratio":"21:9","actions_click":"unset","custom_column":3,"grid_image_desktop":4,"autoplay":false,"loop":false,"show_arrow":false,"show_bullet":true,"show_bullet_mobile":false,"padding_top":0,"padding_bottom":0,"reset_spacing":false}},"custom_liquid_cW9ygK":{"type":"custom-liquid","settings":{"heading":"How low should pendant lights hang?","description":"","text_alignment":"text-left","container":"container","background_color":"","content_liquid":"","padding_top":0,"padding_bottom":0,"reset_spacing":false}},"custom_html_tpAxE8":{"type":"custom-html","settings":{"heading":"","description":"","text_alignment":"text-center","container":"container","background_color":"","content_html":"<style>\n        table {\n            width: 100%;\n            border-collapse: collapse;\n            font-family: Arial, sans-serif;\n        }\n        th, td {\n            border: 1px solid #ddd;\n            padding: 12px;\n            text-align: left;\n        }\n        th {\n            background-color: #f2f2f2;\n            font-weight: bold;\n        }\n        tr:nth-child(even) {\n            background-color: #f9f9f9;\n        }\n        tr:hover {\n            background-color: #f5f5f5;\n        }\n    <\/style>\n    <table>\n        <tbody>\n<tr>\n            <th>Location<\/th>\n            <th>Recommended Height Above Surface<\/th>\n            <th>Additional Considerations<\/th>\n        <\/tr>\n        <tr>\n            <td>Living Room<\/td>\n            <td>5 to 7 feet above seating<\/td>\n            <td>Aim for at least 7 feet of space between the floor and whatever you're hanging.  You can go higher or lower depending on how tall your ceiling is and what looks best to you.<\/td>\n        <\/tr>\n        <tr>\n            <td>Dining Room<\/td>\n            <td>28 to 32 inches above the table<\/td>\n            <td>To figure out the best height to hang a light fixture:\n\nIf your ceiling is higher than 8 feet, for every extra foot, add 3 inches to the fixture's height.\nThe bottom of the light should be about 75 to 85 centimeters (roughly 2.5 to 2.8 feet) above the table.\nMake sure the light isn't in the way when people are trying to see across the table.<\/td>\n        <\/tr>\n        <tr>\n            <td>Kitchen Island<\/td>\n            <td>30 to 36 inches above the countertop<\/td>\n            <td>Another source suggests 2.5 to 3 feet (70-90cm) above the counter. There should be a minimum of 7 feet from the floor to the bottom of the pendant. Consider the size of the pendants and the overall scale of the island when determining placement.<\/td>\n        <\/tr>\n    <\/tbody>\n<\/table>","padding_top":0,"padding_bottom":0,"reset_spacing":false}},"banner_with_text_McfLaN":{"type":"banner-with-text","blocks":{"heading_dng4VB":{"type":"heading","settings":{"title":"Looking to transform your home with stylish lighting?","heading_color":"#111111","heading_fs":40,"heading_fw":500,"heading_tf":"unset","heading_mt":0,"heading_mb":10}},"text_LbEDLK":{"type":"text","settings":{"txt_content":"<p><br\/>Learn all about pendant lights, their types, and why designers love them.<br\/><br\/><\/p>","txt_color":"","txt_fs":16,"txt_fw":400,"txt_tf":"unset","txt_mt":0,"txt_mb":25}},"buttons_3Rx6H8":{"type":"buttons","settings":{"btn_content":"Read More →","button_type":"primary","button_link":"https:\/\/ledsone.co.uk\/pages\/hanging-lights","button_target":false,"b_mt":0,"b_mb":15}}},"block_order":["heading_dng4VB","text_LbEDLK","buttons_3Rx6H8"],"name":"Banner with text","settings":{"container":"container","background_color":"","banner_type":"image","image":"shopify:\/\/shop_images\/pendant_lighting_modern.jpg","video_options":"local","video_url":"https:\/\/www.youtube.com\/watch?v=_9VUPq3SxOc","link":"","hover_effect":"zoom","bn_design":"text_column","banner_height":"depend-image","height_dk":800,"height_tb":600,"height_mb":360,"content_box":"content_in_container","text_bellow_mobile":false,"img_position":"left","banner_width":"col-md-6","column_gap":30,"text_horizontal_position":"left","text_position":"center","text_align":"text-center","content_width":100,"content_bg_color":"","bg_opacity":100,"eb_scrolling":false,"s_text_color":"#111111","s_text_font_size":80,"s_text_font_weight":600,"text_time":10,"text_spacing":50,"padding_top":0,"padding_bottom":0,"reset_spacing":false}}},"order":["38f3b02d-4d55-4285-bac3-806855394e6d","main-collection-heading","custom_html_EigtzR","8498460c-0376-40d1-bafc-199edbe0edfc","439e38df-206c-40a8-9cd5-fc0e5f00f9d3","custom_html_Eh7Kck","product-grid","custom_liquid_z46zMY","custom_text_PYCWrA","banner_image_jQGMQz","custom_liquid_U4pApF","custom_text_RUtjjR","custom_liquid_KeeLkN","custom_text_CmcrEN","gallery_exLdca","custom_liquid_cW9ygK","custom_html_tpAxE8","banner_with_text_McfLaN"]}