{"sections":{"responsive_banner_EpEhUm":{"type":"responsive-banner","disabled":true,"name":"Responsive Banner","settings":{"full_width":true,"desktop_image":"shopify:\/\/shop_images\/Transformer_page_IMG01.jpg","mobile_image":"shopify:\/\/shop_images\/image_-_2025-11-05T121224.117.jpg","link_url":"","heading":"","subheading":"","button_label":"","text_color":"#ffffff","button_bg_color":"#000000","button_text_color":"#ffffff","show_overlay":true,"overlay_color":"#000000","overlay_opacity":30}},"banner_image_d8Q4Ei":{"type":"banner-image","blocks":{"image_banner_BibQbe":{"type":"image_banner","settings":{"banner_type":"image","banner_width":"12","image":"shopify:\/\/shop_images\/wire_cage_shade..jpg","background_color":"","video_options":"local","video_url":"https:\/\/www.youtube.com\/watch?v=_9VUPq3SxOc","link":"https:\/\/ledsone.co.uk\/collections\/wire-cage","color":"default","content_spacing":"default","text_size":"medium","h_text_weight":400,"title":"","subtext":"","content":"","button_type":"primary","btn_content":"","open_link":"_blank"}}},"block_order":["image_banner_BibQbe"],"name":"Banner image","settings":{"show_heading_header":false,"heading":"Title","description":"","text_alignment":"text-center","container":"container","banner_background_color":"","hover_effect":"none","design_banner":"text-below-image","text_position":"top","text_align":"text-left","content_on_mobile":false,"column_gap":10,"padding_top":10,"padding_bottom":0,"reset_spacing":false}},"collection_link_jVyRKX":{"type":"collection-link","blocks":{"link_item_8PJEyq":{"type":"link_item","settings":{"title_collection":"","collection":"dc-5v-transformer"}},"link_item_4C6bHA":{"type":"link_item","settings":{"title_collection":"","collection":"dc-12v-transformer"}},"link_item_wbARLp":{"type":"link_item","settings":{"title_collection":"","collection":"dc-24v-transformer"}},"link_item_mLpAYP":{"type":"link_item","settings":{"title_collection":"","collection":"constant-voltage-transformer"}}},"block_order":["link_item_8PJEyq","link_item_4C6bHA","link_item_wbARLp","link_item_mLpAYP"],"disabled":true,"name":"Collection link","settings":{"heading":"","description":"","text_alignment":"text-center","container":"container","background_color":"","design_collection":"clt-dark","show_count_product":false,"content_width_box_link":100,"link_font_size":16,"link_font_weight":400,"collection_type":"primary","column_gap":30,"padding_top":0,"padding_bottom":0,"reset_spacing":false}},"category_navigation_UWmyGy":{"type":"category-navigation","blocks":{"category_wfXAeg":{"type":"category","settings":{"title":"All","link":"","tag":"","tag_color":"#ff0000","tag_text_color":"#ffffff"}},"category_cLCULU":{"type":"category","settings":{"title":"Women","link":"","tag":"new","tag_color":"#00cc66","tag_text_color":"#ffffff"}},"category_UAhJpM":{"type":"category","settings":{"title":"Men","link":"","tag":"hot","tag_color":"#ff3366","tag_text_color":"#ffffff"}}},"block_order":["category_wfXAeg","category_cLCULU","category_UAhJpM"],"disabled":true,"name":"Category Navigation","settings":{"heading":"Shop by Category"}},"custom_menu_yjNWbX":{"type":"custom-menu","disabled":true,"name":"Custom Menu","settings":{"heading":"","menu":"main-cat-transformers","menu_direction":"row","spacing":8}},"collection_list_HFeWVE":{"type":"collection-list","blocks":{"collection_item_fgawCf":{"type":"collection_item","settings":{"title_collection":"IP67","collection":"","image":"shopify:\/\/shop_images\/image_58__converted.webp"}},"collection_item_KmUVPw":{"type":"collection_item","settings":{"title_collection":"IP20","collection":"","image":"shopify:\/\/shop_images\/image_57__converted.webp"}},"collection_item_jWNhTJ":{"type":"collection_item","settings":{"title_collection":"LED Drivers","collection":"","image":"shopify:\/\/shop_images\/image_56__converted.webp"}},"collection_item_iWKyUQ":{"type":"collection_item","settings":{"title_collection":"IP45","collection":"","image":"shopify:\/\/shop_images\/image_55__converted.webp"}}},"block_order":["collection_item_fgawCf","collection_item_KmUVPw","collection_item_jWNhTJ","collection_item_iWKyUQ"],"disabled":true,"custom_css":[".bls__section:not(.bls__product) .row > * {box-shadow: 10px 10px 20px rgba(0, 0, 0, 0.1); border-radius: 10px; transition: all 0.3s ease; \/* Smooth transition for hover effects *\/}",".bls__section:not(.bls__product) .row > *:hover {box-shadow: 10px 10px 30px rgba(0, 0, 0, 0.15); \/* Stronger shadow on hover *\/ transform: translateY(-5px); \/* Slight lift effect *\/}"],"name":"Collection list","settings":{"heading":"","description":"","text_alignment":"text-center","container":"container","background_color":"","design_layout":"grid","design_collection":"design-2","hover_effect":"none","show_count_product":true,"custom_width_images":false,"width_image":0,"images_style":"square","image_ratio":"4\/3","custom_ratio":"4:3","custom_column":4,"column_gap":30,"autoplay":false,"loop":false,"show_arrow":false,"show_bullet":false,"show_bullet_mobile":false,"reveal_on_scroll":false,"padding_top":24,"padding_bottom":0,"reset_spacing":true}},"custom_featured_grid_wxb4dh":{"type":"custom-featured-grid","name":"Custom Featured Grid","settings":{"main_product_position":"left","grid_gap":20,"section_padding_top":40,"section_padding_bottom":40,"main_product":"modern-drum-lampshade-brushed-silver-colour-retro-style","main_image":"shopify:\/\/shop_images\/Metal_Lampshade_E27_Easy_Fit_Ceiling_Light_Cover.jpg","main_use_product_image":false,"main_show_quicklook":false,"small_product_1":"metal-rustic-red-pattern-vintage-lamp-wire-cage","small_image_1":"shopify:\/\/shop_images\/Industrial_Ceiling_Pendant_Light_Lampshade_Rustic_Modern_Pattern_Easy_Fit_Shade.jpg","small1_use_product_image":false,"small1_image_left":true,"small_product_2":"easy-fit-modern-pattern-pendant-light-metal-drum-lampshade","small_image_2":"shopify:\/\/shop_images\/Easy_Fit_Modern_Pattern_White_Metal_Drum_Lampshade_2513.jpg","small2_use_product_image":false,"small2_image_left":false}},"lookbook_JQcnHT":{"type":"lookbook","blocks":{"lookbook_taDqh4":{"type":"lookbook","settings":{"image":"shopify:\/\/shop_images\/Easy_Fit_Pendant_Light_Pattern_Cage_Metal_Drum_Lampshade.jpg","position_top_1":66,"position_left_1":70,"product_1":"easy-fit-pendant-light-pattern-metal-drum-lampshade","position_top_2":26,"position_left_2":50,"product_2":"","position_top_3":61,"position_left_3":48,"product_3":"","position_top_4":0,"position_left_4":0,"product_4":"","position_top_5":20,"position_left_5":0,"product_5":"","position_top_6":20,"position_left_6":0,"product_6":"","position_top_7":20,"position_left_7":0,"product_7":"","position_top_8":20,"position_left_8":0,"product_8":"","position_top_9":20,"position_left_9":0,"product_9":"","position_top_10":20,"position_left_10":0,"product_10":"","position_top_11":20,"position_left_11":0,"product_11":"","position_top_12":20,"position_left_12":0,"product_12":"","position_top_13":20,"position_left_13":0,"product_13":"","position_top_14":20,"position_left_14":0,"product_14":"","position_top_15":20,"position_left_15":0,"product_15":"","position_top_16":20,"position_left_16":0,"product_16":"","position_top_17":20,"position_left_17":0,"product_17":"","position_top_18":20,"position_left_18":0,"product_18":"","position_top_19":20,"position_left_19":0,"product_19":"","position_top_20":20,"position_left_20":0,"product_20":""}},"lookbook_rwcMAN":{"type":"lookbook","settings":{"image":"shopify:\/\/shop_images\/Metal_Cage_Lampshade_Ceiling_Pendant_Light_Fixtures.jpg","position_top_1":64,"position_left_1":69,"product_1":"retro-light-shades-industrial-ceiling-black-metal-lamp-cage","position_top_2":26,"position_left_2":50,"product_2":"","position_top_3":61,"position_left_3":48,"product_3":"","position_top_4":0,"position_left_4":0,"product_4":"","position_top_5":20,"position_left_5":0,"product_5":"","position_top_6":20,"position_left_6":0,"product_6":"","position_top_7":20,"position_left_7":0,"product_7":"","position_top_8":20,"position_left_8":0,"product_8":"","position_top_9":20,"position_left_9":0,"product_9":"","position_top_10":20,"position_left_10":0,"product_10":"","position_top_11":20,"position_left_11":0,"product_11":"","position_top_12":20,"position_left_12":0,"product_12":"","position_top_13":20,"position_left_13":0,"product_13":"","position_top_14":20,"position_left_14":0,"product_14":"","position_top_15":20,"position_left_15":0,"product_15":"","position_top_16":20,"position_left_16":0,"product_16":"","position_top_17":20,"position_left_17":0,"product_17":"","position_top_18":20,"position_left_18":0,"product_18":"","position_top_19":20,"position_left_19":0,"product_19":"","position_top_20":20,"position_left_20":0,"product_20":""}},"lookbook_RtyW3x":{"type":"lookbook","disabled":true,"settings":{"image":"shopify:\/\/shop_images\/wire_wall_light.jpg","position_top_1":46,"position_left_1":52,"product_1":"black-wall-lamp-on-the-left-resin-bird-wall-sconce-4779","position_top_2":26,"position_left_2":50,"product_2":"","position_top_3":61,"position_left_3":48,"product_3":"","position_top_4":0,"position_left_4":0,"product_4":"","position_top_5":20,"position_left_5":0,"product_5":"","position_top_6":20,"position_left_6":0,"product_6":"","position_top_7":20,"position_left_7":0,"product_7":"","position_top_8":20,"position_left_8":0,"product_8":"","position_top_9":20,"position_left_9":0,"product_9":"","position_top_10":20,"position_left_10":0,"product_10":"","position_top_11":20,"position_left_11":0,"product_11":"","position_top_12":20,"position_left_12":0,"product_12":"","position_top_13":20,"position_left_13":0,"product_13":"","position_top_14":20,"position_left_14":0,"product_14":"","position_top_15":20,"position_left_15":0,"product_15":"","position_top_16":20,"position_left_16":0,"product_16":"","position_top_17":20,"position_left_17":0,"product_17":"","position_top_18":20,"position_left_18":0,"product_18":"","position_top_19":20,"position_left_19":0,"product_19":"","position_top_20":20,"position_left_20":0,"product_20":""}}},"block_order":["lookbook_taDqh4","lookbook_rwcMAN","lookbook_RtyW3x"],"name":"Lookbook","settings":{"heading":"","description":"","text_alignment":"text-center","container":"container","background_color":"","design_layout":"slider","dot_type":"icon","aspect_ratio":"1\/1","custom_ratio":"21:9","column_gap":10,"slider_lookbook_items":2,"action_click":"fancybox","popup_type":"popup_quickview","autoplay":false,"loop":false,"show_arrow":false,"show_bullet":true,"show_bullet_mobile":false,"padding_top":0,"padding_bottom":0,"reset_spacing":false}},"video_mEcTLt":{"type":"video","name":"Video","settings":{"container":"container","reset_spacing":true,"video_type":"background","aspect_ratio":"1\/1","custom_ratio":"21:9","content_box":"content_in_container","text_position":"position-cc","text_content":"text-center","heading_size":80,"thumbnail_subheading":"","thumbnail_heading":"","thumbnail_desc":"","thumbnail_color":"text-black","thumbnail_button":"Shop now","thumbnail_link":"","video_options":"local","video_local":"shopify:\/\/files\/videos\/high quality Wire Cages.mp4","video_url":"https:\/\/youtu.be\/dLVSAOttr2E","video_height":"height_default","desktop_height":600,"mobile_height":250,"video_full_screen":false}},"product_single_xhwEBg":{"type":"product-single","custom_css":[".container {background-color: #f8fafc; \/* Soft neutral tone *\/ border-radius: 12px; \/* Smooth rounded edges *\/ box-shadow: 0 4px 12px rgba(0, 0, 0, 0.05); \/* Subtle professional shadow *\/ padding: 24px; \/* Balanced inner spacing *\/ margin: 20px auto; \/* Centered with spacing *\/ max-width: 1200px; \/* Clean readable width *\/ transition: all 0.3s ease; \/* Smooth hover or layout transitions *\/}",".container:hover {box-shadow: 0 6px 16px rgba(0, 0, 0, 0.08); \/* Slightly lifted hover effect *\/}"],"name":"Product single","settings":{"heading":"","description":"","text_alignment":"text-center","container":"container","bg_color":"","single_product":"vintage-tree-pattern-white-metal-wire-frame-wire-cage-lamp-light","column_gap":20,"show_review":true,"show_short_description":true,"show_vendor":true,"show_sku":false,"show_type":true,"show_available":true,"show_collection":false,"button_animation":"flash-move","show_buy_now":true,"show_countdown":false,"countdown_message":"Hurry up! Sale end in:","padding_top":0,"padding_bottom":0,"reset_spacing":true}},"custom_featured_grid_zWm7LJ":{"type":"custom-featured-grid","name":"Custom Featured Grid","settings":{"main_product_position":"right","grid_gap":20,"section_padding_top":40,"section_padding_bottom":40,"main_product":"vintage-red-metal-cage-industrial-wire-frame-pendant-light-loft-ceiling-lamp-shade","main_image":"shopify:\/\/shop_images\/Vintage_Geometric_Cage_Lampshade_20x20cm_E27_Base.jpg","main_use_product_image":false,"main_show_quicklook":false,"small_product_1":"metal-easy-fit-black-wire-cage","small_image_1":"shopify:\/\/shop_images\/Diamond_Easy_Fit_Lamp_Shade_Metal_Cage.jpg","small1_use_product_image":false,"small1_image_left":true,"small_product_2":"modern-geometric-diamond-pendant-shade-ceiling-light-lampshade-black-metal-wire-frame-cages","small2_use_product_image":false,"small2_image_left":false}},"lookbook_DC4rpL":{"type":"lookbook","blocks":{"lookbook_ctTiBq":{"type":"lookbook","settings":{"image":"shopify:\/\/shop_images\/Screenshot2024-03-21114044.png","position_top_1":45,"position_left_1":24,"product_1":"easy-fit-rustic-red-colour-drum-lampshade-modern-metal-shade-retro-style","position_top_2":26,"position_left_2":50,"product_2":"","position_top_3":61,"position_left_3":48,"product_3":"","position_top_4":0,"position_left_4":0,"product_4":"","position_top_5":20,"position_left_5":0,"product_5":"","position_top_6":20,"position_left_6":0,"product_6":"","position_top_7":20,"position_left_7":0,"product_7":"","position_top_8":20,"position_left_8":0,"product_8":"","position_top_9":20,"position_left_9":0,"product_9":"","position_top_10":20,"position_left_10":0,"product_10":"","position_top_11":20,"position_left_11":0,"product_11":"","position_top_12":20,"position_left_12":0,"product_12":"","position_top_13":20,"position_left_13":0,"product_13":"","position_top_14":20,"position_left_14":0,"product_14":"","position_top_15":20,"position_left_15":0,"product_15":"","position_top_16":20,"position_left_16":0,"product_16":"","position_top_17":20,"position_left_17":0,"product_17":"","position_top_18":20,"position_left_18":0,"product_18":"","position_top_19":20,"position_left_19":0,"product_19":"","position_top_20":20,"position_left_20":0,"product_20":""}},"lookbook_NXcCad":{"type":"lookbook","settings":{"image":"shopify:\/\/shop_images\/1999.jpg","position_top_1":55,"position_left_1":51,"product_1":"metal-pattern-vintage-lamp-wire-cage-white-lamp-light","position_top_2":26,"position_left_2":50,"product_2":"","position_top_3":61,"position_left_3":48,"product_3":"","position_top_4":0,"position_left_4":0,"product_4":"","position_top_5":20,"position_left_5":0,"product_5":"","position_top_6":20,"position_left_6":0,"product_6":"","position_top_7":20,"position_left_7":0,"product_7":"","position_top_8":20,"position_left_8":0,"product_8":"","position_top_9":20,"position_left_9":0,"product_9":"","position_top_10":20,"position_left_10":0,"product_10":"","position_top_11":20,"position_left_11":0,"product_11":"","position_top_12":20,"position_left_12":0,"product_12":"","position_top_13":20,"position_left_13":0,"product_13":"","position_top_14":20,"position_left_14":0,"product_14":"","position_top_15":20,"position_left_15":0,"product_15":"","position_top_16":20,"position_left_16":0,"product_16":"","position_top_17":20,"position_left_17":0,"product_17":"","position_top_18":20,"position_left_18":0,"product_18":"","position_top_19":20,"position_left_19":0,"product_19":"","position_top_20":20,"position_left_20":0,"product_20":""}}},"block_order":["lookbook_ctTiBq","lookbook_NXcCad"],"name":"Lookbook","settings":{"heading":"","description":"","text_alignment":"text-center","container":"container","background_color":"","design_layout":"slider","dot_type":"icon","aspect_ratio":"1\/1","custom_ratio":"21:9","column_gap":10,"slider_lookbook_items":2,"action_click":"fancybox","popup_type":"popup_quickview","autoplay":false,"loop":false,"show_arrow":false,"show_bullet":true,"show_bullet_mobile":false,"padding_top":0,"padding_bottom":0,"reset_spacing":false}},"main":{"type":"main-page","disabled":true,"settings":{}},"product_single_Ez6mq7":{"type":"product-single","name":"Product single","settings":{"heading":"","description":"","text_alignment":"text-center","container":"container","bg_color":"","single_product":"modern-drum-lampshade-black-colour-retro-style","column_gap":20,"show_review":true,"show_short_description":true,"show_vendor":false,"show_sku":true,"show_type":true,"show_available":true,"show_collection":false,"button_animation":"flash-move","show_buy_now":true,"show_countdown":false,"countdown_message":"Hurry up! Sale end in:","padding_top":0,"padding_bottom":0,"reset_spacing":false}},"product_gallery_zp7Rf7":{"type":"product_gallery","blocks":{"gallery_item_GYYpT7":{"type":"gallery_item","settings":{"image":"shopify:\/\/shop_images\/2617up.jpg","title":"Cage Retro Industrial Ceiling Pendant Light Lampshade","subtitle":"","product":"lampshade-cage-retro-modern-industrial-ceiling-light-pendant-lamp","feedback":"Happily surprised at how nice they were.very happy","rating":5}},"gallery_item_4FDYPp":{"type":"gallery_item","settings":{"image":"shopify:\/\/shop_images\/Vintage_Metal_Cage_Industrial_Wire_Pendant_Light_Lampshade.jpg","title":"Vintage Metal Cage Industrial Wire Pendant Light Lampshade","subtitle":"","product":"vintage-metal-cage-industrial-wire-pendant-light-lampshade-6092","feedback":"Nice product fits my light fitting fine and goes well with rest of kitchen","rating":5}},"gallery_item_QMRUHW":{"type":"gallery_item","settings":{"image":"shopify:\/\/shop_images\/2430up.jpg","title":"Modern Retro Style Drum Metal Ceiling Pendant Lampshade","subtitle":"","product":"brushed-brass-colour-drum-lampshade-modern-metal-shade-retro-style","feedback":"I was very pleased with the lampshades when they arrived and were delivered very quickly with no fuss.","rating":5}}},"block_order":["gallery_item_GYYpT7","gallery_item_4FDYPp","gallery_item_QMRUHW"],"name":"Product Gallery","settings":{"section_title":"Customer Favorites","desktop_columns":3}}},"order":["responsive_banner_EpEhUm","banner_image_d8Q4Ei","collection_link_jVyRKX","category_navigation_UWmyGy","custom_menu_yjNWbX","collection_list_HFeWVE","custom_featured_grid_wxb4dh","lookbook_JQcnHT","video_mEcTLt","product_single_xhwEBg","custom_featured_grid_zWm7LJ","lookbook_DC4rpL","main","product_single_Ez6mq7","product_gallery_zp7Rf7"]}